modethirteen/mkdocs/__init__.py
modethirteen/mkdocs/metadata/__init__.py
mkdocs_techdocs-0.0.5.dist-info/METADATA
mkdocs_techdocs-0.0.5.dist-info/WHEEL
mkdocs_techdocs-0.0.5.dist-info/entry_points.txt
mkdocs_techdocs-0.0.5.dist-info/licenses/LICENSE
mkdocs_techdocs-0.0.5.dist-info/RECORD
