Metadata-Version: 2.1
Name: mkdocs-techdocs
Version: 0.0.5
Summary: A collection of MkDocs plugins designed to work with Spotify's TechDocs system
Author-email: James Andrew Vaughn <jamesvaughn@modethirteen.com>
License-File: LICENSE
Requires-Dist: mkdocs
